<Gesture Name="v01" Number="01" NumPts="153"><Point X="138" Y="355" /><Point X="138" Y="354" /><Point X="138" Y="353" /><Point X="139" Y="352" /><Point X="140" Y="351" /><Point X="140" Y="349" /><Point X="141" Y="348" /><Point X="143" Y="346" /><Point X="143" Y="345" /><Point X="143" Y="344" /><Point X="144" Y="343" /><Point X="145" Y="342" /><Point X="145" Y="341" /><Point X="145" Y="340" /><Point X="146" Y="340" /><Point X="146" Y="339" /><Point X="146" Y="338" /><Point X="146" Y="337" /><Point X="147" Y="337" /><Point X="147" Y="336" /><Point X="147" Y="335" /><Point X="148" Y="335" /><Point X="149" Y="333" /><Point X="149" Y="332" /><Point X="150" Y="330" /><Point X="150" Y="329" /><Point X="150" Y="328" /><Point X="151" Y="328" /><Point X="151" Y="327" /><Point X="151" Y="326" /><Point X="151" Y="325" /><Point X="152" Y="325" /><Point X="152" Y="324" /><Point X="153" Y="322" /><Point X="153" Y="320" /><Point X="154" Y="319" /><Point X="154" Y="318" /><Point X="155" Y="316" /><Point X="156" Y="314" /><Point X="157" Y="313" /><Point X="158" Y="310" /><Point X="160" Y="307" /><Point X="160" Y="306" /><Point X="161" Y="305" /><Point X="162" Y="304" /><Point X="162" Y="302" /><Point X="163" Y="302" /><Point X="163" Y="300" /><Point X="163" Y="299" /><Point X="164" Y="297" /><Point X="165" Y="295" /><Point X="166" Y="294" /><Point X="167" Y="292" /><Point X="168" Y="291" /><Point X="168" Y="289" /><Point X="169" Y="288" /><Point X="170" Y="286" /><Point X="170" Y="285" /><Point X="171" Y="285" /><Point X="171" Y="284" /><Point X="171" Y="283" /><Point X="171" Y="282" /><Point X="172" Y="281" /><Point X="173" Y="280" /><Point X="173" Y="279" /><Point X="173" Y="278" /><Point X="174" Y="277" /><Point X="175" Y="276" /><Point X="176" Y="274" /><Point X="177" Y="272" /><Point X="178" Y="271" /><Point X="178" Y="270" /><Point X="179" Y="269" /><Point X="179" Y="268" /><Point X="180" Y="268" /><Point X="179" Y="268" /><Point X="179" Y="269" /><Point X="179" Y="270" /><Point X="179" Y="271" /><Point X="180" Y="273" /><Point X="181" Y="275" /><Point X="182" Y="276" /><Point X="183" Y="278" /><Point X="184" Y="280" /><Point X="186" Y="281" /><Point X="186" Y="283" /><Point X="187" Y="284" /><Point X="188" Y="284" /><Point X="188" Y="285" /><Point X="189" Y="286" /><Point X="189" Y="287" /><Point X="190" Y="287" /><Point X="191" Y="289" /><Point X="192" Y="290" /><Point X="193" Y="291" /><Point X="195" Y="293" /><Point X="196" Y="296" /><Point X="198" Y="298" /><Point X="199" Y="298" /><Point X="200" Y="300" /><Point X="200" Y="301" /><Point X="201" Y="301" /><Point X="202" Y="303" /><Point X="203" Y="303" /><Point X="203" Y="305" /><Point X="206" Y="308" /><Point X="208" Y="312" /><Point X="210" Y="315" /><Point X="212" Y="317" /><Point X="213" Y="319" /><Point X="213" Y="320" /><Point X="214" Y="320" /><Point X="214" Y="321" /><Point X="214" Y="322" /><Point X="214" Y="323" /><Point X="215" Y="323" /><Point X="215" Y="324" /><Point X="215" Y="325" /><Point X="216" Y="326" /><Point X="216" Y="327" /><Point X="217" Y="330" /><Point X="217" Y="331" /><Point X="218" Y="332" /><Point X="218" Y="333" /><Point X="218" Y="334" /><Point X="219" Y="335" /><Point X="220" Y="335" /><Point X="220" Y="336" /><Point X="220" Y="337" /><Point X="220" Y="338" /><Point X="221" Y="338" /><Point X="221" Y="339" /><Point X="221" Y="340" /><Point X="222" Y="341" /><Point X="223" Y="341" /><Point X="223" Y="342" /><Point X="223" Y="343" /><Point X="224" Y="343" /><Point X="224" Y="344" /><Point X="225" Y="345" /><Point X="225" Y="346" /><Point X="226" Y="346" /><Point X="226" Y="347" /><Point X="227" Y="347" /><Point X="227" Y="348" /><Point X="228" Y="349" /><Point X="229" Y="350" /><Point X="229" Y="351" /><Point X="229" Y="352" /><Point X="230" Y="353" /><Point X="230" Y="354" /><Point X="231" Y="354" /><Point X="231" Y="355" /></Gesture>